graphmix/__init__.py
graphmix/__main__.py
graphmix/cli.py
graphmix/config.py
graphmix/location.py
graphmix/chemistry/__init__.py
graphmix/chemistry/chemical.py
graphmix/chemistry/dilution.py
graphmix/chemistry/units.py
graphmix/chemistry/adapters/__init__.py
graphmix/chemistry/adapters/repository.py
graphmix/chemistry/service_layer/__init__.py
graphmix/chemistry/service_layer/pubchem.py
graphmix/chemistry/service_layer/registry.py
graphmix/chemistry/service_layer/unit_of_work.py
graphmix/core/__init__.py
graphmix/core/repository.py
graphmix/core/unit_of_work.py
graphmix/core/util.py
graphmix/core/sqlmodel/__init__.py
graphmix/core/sqlmodel/repository.py
graphmix/core/sqlmodel/unit_of_work.py
graphmix/experiment/__init__.py
graphmix/experiment/experiment.py
graphmix/graph/__init__.py
graphmix/graph/drawing.py
graphmix/graph/model.py
graphmix/graph/node.py
graphmix/graph/protocol.py
graphmix/graph/solution.py
graphmix/graph/builder/__init__.py
graphmix/graph/builder/builder.py
graphmix/graph/builder/standards.py
graphmix/liquid_handling/__init__.py
graphmix/liquid_handling/liquid_handler.py
graphmix-0.0.2.dist-info/METADATA
graphmix-0.0.2.dist-info/WHEEL
graphmix-0.0.2.dist-info/licenses/AUTHORS.rst
graphmix-0.0.2.dist-info/licenses/LICENSE
graphmix-0.0.2.dist-info/RECORD
