Metadata-Version: 2.3
Name: graphmix
Version: 0.0.2
Summary: Intelligent experiment planning and optimization powered by graph algorithms.
Project-URL: Documentation, https://python-graphmix.readthedocs.io/
Project-URL: Changelog, https://python-graphmix.readthedocs.io/en/latest/changelog.html
Project-URL: Issues, https://github.com/jt05610/python-graphmix/issues
Project-URL: Repository, https://github.com/jt05610/python-graphmix.git
Project-URL: Homepage, https://github.com/jt05610/python-graphmix
Author-email: Jonathan Taylor <jonrtaylor12@gmail.com>
Maintainer-email: Jonathan Taylor <jonrtaylor12@gmail.com>
License: MIT License
License-File: AUTHORS.rst
License-File: LICENSE
Classifier: Development Status :: 3 - Alpha
Classifier: Intended Audience :: Developers
Classifier: License :: OSI Approved :: MIT License
Classifier: Operating System :: Microsoft :: Windows
Classifier: Operating System :: POSIX
Classifier: Operating System :: Unix
Classifier: Programming Language :: Python
Classifier: Programming Language :: Python :: 3
Classifier: Programming Language :: Python :: 3 :: Only
Classifier: Programming Language :: Python :: 3.10
Classifier: Programming Language :: Python :: 3.11
Classifier: Programming Language :: Python :: 3.12
Classifier: Topic :: Utilities
Requires-Python: >=3.10
Requires-Dist: matplotlib~=3.9.0
Requires-Dist: networkx~=3.3
Requires-Dist: pint~=0.23
Requires-Dist: pydantic~=2.7.1
Requires-Dist: requests-ratelimiter~=0.6.0
Requires-Dist: requests~=2.32.2
Requires-Dist: scipy~=1.13.1
Requires-Dist: sqlmodel~=0.0.18
